py_clubhouse/__init__.py
py_clubhouse/api.py
py_clubhouse/clubhouse.py
py_clubhouse/const.py
py_clubhouse/core/__init__.py
py_clubhouse/core/request.py
py_clubhouse/core/utils.py
py_clubhouse/endpoints.py
py_clubhouse/models/__init__.py
py_clubhouse/models/base.py
py_clubhouse/models/branch.py
py_clubhouse/models/comment.py
py_clubhouse/models/commit.py
py_clubhouse/models/external_ticket.py
py_clubhouse/models/file.py
py_clubhouse/models/label.py
py_clubhouse/models/linked_file.py
py_clubhouse/models/pull_request.py
py_clubhouse/models/story.py
py_clubhouse/models/story_link.py
py_clubhouse/models/story_search_results.py
py_clubhouse/models/story_stats.py
py_clubhouse/models/task.py
py_clubhouse/models/typed_story_link.py
py_clubhouse/models/workflow.py
py_clubhouse/models/workflow_state.py
py_clubhouse-0.1.2.dist-info/WHEEL
py_clubhouse-0.1.2.dist-info/METADATA
py_clubhouse-0.1.2.dist-info/RECORD
