Metadata-Version: 2.1
Name: py-clubhouse
Version: 0.1.2
Summary: Python client for Clubhouse
Home-page: https://github.com/nickatnight/py-clubhouse/
License: MIT
Author: nickatnight
Author-email: nickkelly.858@gmail.com
Requires-Python: >=3.7,<4.0
Classifier: Environment :: Web Environment
Classifier: Intended Audience :: Developers
Classifier: License :: OSI Approved :: MIT License
Classifier: Operating System :: OS Independent
Classifier: Programming Language :: Python
Classifier: Programming Language :: Python :: 3
Classifier: Programming Language :: Python :: 3.7
Classifier: Programming Language :: Python :: 3.8
Classifier: Programming Language :: Python :: 3.9
Requires-Dist: requests (>=2.24.0,<3.0.0)
Project-URL: Repository, https://github.com/nickatnight/py-clubhouse/
